fsm_assignments/problem2_traffic/traffic_light.v
module traffic_light(
    input  wire clk,
    input  wire rst,   // synchronous active-high reset
    input  wire tick,  // 1-cycle pulse (1Hz or faster in sim)

    output reg ns_g, ns_y, ns_r,
    output reg ew_g, ew_y, ew_r
);

    // States
    localparam S_NS_G = 2'b00;
    localparam S_NS_Y = 2'b01;
    localparam S_EW_G = 2'b10;
    localparam S_EW_Y = 2'b11;

    reg [1:0] state, next_state;
    reg [2:0] count; // counts ticks within each phase

    // State register
    always @(posedge clk) begin
        if (rst) begin
            state <= S_NS_G;
            count <= 0;
        end else begin
            state <= next_state;
            if (tick) begin
                if ((state == S_NS_G && count == 4) ||
                    (state == S_NS_Y && count == 1) ||
                    (state == S_EW_G && count == 4) ||
                    (state == S_EW_Y && count == 1))
                    count <= 0; // reset counter on transition
                else
                    count <= count + 1;
            end
        end
    end

    // Next state logic
    always @(*) begin
        next_state = state;
        case (state)
            S_NS_G: if (tick && count == 4) next_state = S_NS_Y;
            S_NS_Y: if (tick && count == 1) next_state = S_EW_G;
            S_EW_G: if (tick && count == 4) next_state = S_EW_Y;
            S_EW_Y: if (tick && count == 1) next_state = S_NS_G;
        endcase
    end

    // Output logic (Moore: based only on state)
    always @(*) begin
        ns_g=0; ns_y=0; ns_r=0;
        ew_g=0; ew_y=0; ew_r=0;

        case (state)
            S_NS_G: begin ns_g=1; ew_r=1; end
            S_NS_Y: begin ns_y=1; ew_r=1; end
            S_EW_G: begin ew_g=1; ns_r=1; end
            S_EW_Y: begin ew_y=1; ns_r=1; end
        endcase
    end
endmodule

fsm_assignments/problem2_traffic/tb_traffic_light.v
module tb_traffic_light;
    reg clk, rst, tick;
    wire ns_g, ns_y, ns_r, ew_g, ew_y, ew_r;

    traffic_light dut(
        .clk(clk), .rst(rst), .tick(tick),
        .ns_g(ns_g), .ns_y(ns_y), .ns_r(ns_r),
        .ew_g(ew_g), .ew_y(ew_y), .ew_r(ew_r)
    );

    always #5 clk = ~clk;  // clock

    integer cyc;

    initial begin
        $dumpfile("dump.vcd");
        $dumpvars(0, tb_traffic_light);

        clk = 0; rst = 1; tick = 0;
        cyc = 0;
        #12 rst = 0;

        // Generate fast tick: one tick every 20 cycles
        forever begin
            @(posedge clk);
            cyc = cyc + 1;
            if (cyc % 20 == 0) tick = 1;
            else tick = 0;
        end
    end

    initial begin
        #2000; // run enough cycles
        $finish;
    end
endmodule

fsm_assignments/problem2_traffic/waves/dump.vcd
$date
	Tue Aug 19 10:21:32 2025
$end
$version
	Icarus Verilog
$end
$timescale
	1s
$end
$scope module tb_traffic_light $end
$var wire 1 ! ns_y $end
$var wire 1 " ns_r $end
$var wire 1 # ns_g $end
$var wire 1 $ ew_y $end
$var wire 1 % ew_r $end
$var wire 1 & ew_g $end
$var reg 1 ' clk $end
$var reg 1 ( rst $end
$var reg 1 ) tick $end
$var integer 32 * cyc [31:0] $end
$scope module dut $end
$var wire 1 ' clk $end
$var wire 1 ( rst $end
$var wire 1 ) tick $end
$var parameter 2 + S_EW_G $end
$var parameter 2 , S_EW_Y $end
$var parameter 2 - S_NS_G $end
$var parameter 2 . S_NS_Y $end
$var reg 3 / count [2:0] $end
$var reg 1 & ew_g $end
$var reg 1 % ew_r $end
$var reg 1 $ ew_y $end
$var reg 2 0 next_state [1:0] $end
$var reg 1 # ns_g $end
$var reg 1 " ns_r $end
$var reg 1 ! ns_y $end
$var reg 2 1 state [1:0] $end
$upscope $end
$upscope $end
$enddefinitions $end
$comment Show the parameter values. $end
$dumpall
b1 .
b0 -
b11 ,
b10 +
$end
#0
$dumpvars
bx 1
bx 0
bx /
b0 *
0)
1(
0'
x&
x%
x$
x#
x"
x!
$end
#5
1%
0$
0&
0"
0!
1#
b0 0
b0 /
b0 1
1'
#10
0'
#12
0(
#15
b1 *
1'
#20
0'
#25
b10 *
1'
#30
0'
#35
b11 *
1'
#40
0'
#45
b100 *
1'
#50
0'
#55
b101 *
1'
#60
0'
#65
b110 *
1'
#70
0'
#75
b111 *
1'
#80
0'
#85
b1000 *
1'
#90
0'
#95
b1001 *
1'
#100
0'
#105
b1010 *
1'
#110
0'
#115
b1011 *
1'
#120
0'
#125
b1100 *
1'
#130
0'
#135
b1101 *
1'
#140
0'
#145
b1110 *
1'
#150
0'
#155
b1111 *
1'
#160
0'
#165
b10000 *
1'
#170
0'
#175
b10001 *
1'
#180
0'
#185
b10010 *
1'
#190
0'
#195
b10011 *
1'
#200
0'
#205
1)
b10100 *
1'
#210
0'
#215
0)
b10101 *
1'
#220
0'
#225
b10110 *
1'
#230
0'
#235
b10111 *
1'
#240
0'
#245
b11000 *
1'
#250
0'
#255
b11001 *
1'
#260
0'
#265
b11010 *
1'
#270
0'
#275
b11011 *
1'
#280
0'
#285
b11100 *
1'
#290
0'
#295
b11101 *
1'
#300
0'
#305
b11110 *
1'
#310
0'
#315
b11111 *
1'
#320
0'
#325
b100000 *
1'
#330
0'
#335
b100001 *
1'
#340
0'
#345
b100010 *
1'
#350
0'
#355
b100011 *
1'
#360
0'
#365
b100100 *
1'
#370
0'
#375
b100101 *
1'
#380
0'
#385
b100110 *
1'
#390
0'
#395
b100111 *
1'
#400
0'
#405
1)
b101000 *
1'
#410
0'
#415
0)
b101001 *
1'
#420
0'
#425
b101010 *
1'
#430
0'
#435
b101011 *
1'
#440
0'
#445
b101100 *
1'
#450
0'
#455
b101101 *
1'
#460
0'
#465
b101110 *
1'
#470
0'
#475
b101111 *
1'
#480
0'
#485
b110000 *
1'
#490
0'
#495
b110001 *
1'
#500
0'
#505
b110010 *
1'
#510
0'
#515
b110011 *
1'
#520
0'
#525
b110100 *
1'
#530
0'
#535
b110101 *
1'
#540
0'
#545
b110110 *
1'
#550
0'
#555
b110111 *
1'
#560
0'
#565
b111000 *
1'
#570
0'
#575
b111001 *
1'
#580
0'
#585
b111010 *
1'
#590
0'
#595
b111011 *
1'
#600
0'
#605
1)
b111100 *
1'
#610
0'
#615
0)
b111101 *
1'
#620
0'
#625
b111110 *
1'
#630
0'
#635
b111111 *
1'
#640
0'
#645
b1000000 *
1'
#650
0'
#655
b1000001 *
1'
#660
0'
#665
b1000010 *
1'
#670
0'
#675
b1000011 *
1'
#680
0'
#685
b1000100 *
1'
#690
0'
#695
b1000101 *
1'
#700
0'
#705
b1000110 *
1'
#710
0'
#715
b1000111 *
1'
#720
0'
#725
b1001000 *
1'
#730
0'
#735
b1001001 *
1'
#740
0'
#745
b1001010 *
1'
#750
0'
#755
b1001011 *
1'
#760
0'
#765
b1001100 *
1'
#770
0'
#775
b1001101 *
1'
#780
0'
#785
b1001110 *
1'
#790
0'
#795
b1001111 *
1'
#800
0'
#805
1)
b1010000 *
1'
#810
0'
#815
0)
b1010001 *
1'
#820
0'
#825
b1010010 *
1'
#830
0'
#835
b1010011 *
1'
#840
0'
#845
b1010100 *
1'
#850
0'
#855
b1010101 *
1'
#860
0'
#865
b1010110 *
1'
#870
0'
#875
b1010111 *
1'
#880
0'
#885
b1011000 *
1'
#890
0'
#895
b1011001 *
1'
#900
0'
#905
b1011010 *
1'
#910
0'
#915
b1011011 *
1'
#920
0'
#925
b1011100 *
1'
#930
0'
#935
b1011101 *
1'
#940
0'
#945
b1011110 *
1'
#950
0'
#955
b1011111 *
1'
#960
0'
#965
b1100000 *
1'
#970
0'
#975
b1100001 *
1'
#980
0'
#985
b1100010 *
1'
#990
0'
#995
b1100011 *
1'
#1000
0'
#1005
1)
b1100100 *
1'
#1010
0'
#1015
0)
b1100101 *
1'
#1020
0'
#1025
b1100110 *
1'
#1030
0'
#1035
b1100111 *
1'
#1040
0'
#1045
b1101000 *
1'
#1050
0'
#1055
b1101001 *
1'
#1060
0'
#1065
b1101010 *
1'
#1070
0'
#1075
b1101011 *
1'
#1080
0'
#1085
b1101100 *
1'
#1090
0'
#1095
b1101101 *
1'
#1100
0'
#1105
b1101110 *
1'
#1110
0'
#1115
b1101111 *
1'
#1120
0'
#1125
b1110000 *
1'
#1130
0'
#1135
b1110001 *
1'
#1140
0'
#1145
b1110010 *
1'
#1150
0'
#1155
b1110011 *
1'
#1160
0'
#1165
b1110100 *
1'
#1170
0'
#1175
b1110101 *
1'
#1180
0'
#1185
b1110110 *
1'
#1190
0'
#1195
b1110111 *
1'
#1200
0'
#1205
1)
b1111000 *
1'
#1210
0'
#1215
0)
b1111001 *
1'
#1220
0'
#1225
b1111010 *
1'
#1230
0'
#1235
b1111011 *
1'
#1240
0'
#1245
b1111100 *
1'
#1250
0'
#1255
b1111101 *
1'
#1260
0'
#1265
b1111110 *
1'
#1270
0'
#1275
b1111111 *
1'
#1280
0'
#1285
b10000000 *
1'
#1290
0'
#1295
b10000001 *
1'
#1300
0'
#1305
b10000010 *
1'
#1310
0'
#1315
b10000011 *
1'
#1320
0'
#1325
b10000100 *
1'
#1330
0'
#1335
b10000101 *
1'
#1340
0'
#1345
b10000110 *
1'
#1350
0'
#1355
b10000111 *
1'
#1360
0'
#1365
b10001000 *
1'
#1370
0'
#1375
b10001001 *
1'
#1380
0'
#1385
b10001010 *
1'
#1390
0'
#1395
b10001011 *
1'
#1400
0'
#1405
1)
b10001100 *
1'
#1410
0'
#1415
0)
b10001101 *
1'
#1420
0'
#1425
b10001110 *
1'
#1430
0'
#1435
b10001111 *
1'
#1440
0'
#1445
b10010000 *
1'
#1450
0'
#1455
b10010001 *
1'
#1460
0'
#1465
b10010010 *
1'
#1470
0'
#1475
b10010011 *
1'
#1480
0'
#1485
b10010100 *
1'
#1490
0'
#1495
b10010101 *
1'
#1500
0'
#1505
b10010110 *
1'
#1510
0'
#1515
b10010111 *
1'
#1520
0'
#1525
b10011000 *
1'
#1530
0'
#1535
b10011001 *
1'
#1540
0'
#1545
b10011010 *
1'
#1550
0'
#1555
b10011011 *
1'
#1560
0'
#1565
b10011100 *
1'
#1570
0'
#1575
b10011101 *
1'
#1580
0'
#1585
b10011110 *
1'
#1590
0'
#1595
b10011111 *
1'
#1600
0'
#1605
1)
b10100000 *
1'
#1610
0'
#1615
0)
b10100001 *
1'
#1620
0'
#1625
b10100010 *
1'
#1630
0'
#1635
b10100011 *
1'
#1640
0'
#1645
b10100100 *
1'
#1650
0'
#1655
b10100101 *
1'
#1660
0'
#1665
b10100110 *
1'
#1670
0'
#1675
b10100111 *
1'
#1680
0'
#1685
b10101000 *
1'
#1690
0'
#1695
b10101001 *
1'
#1700
0'
#1705
b10101010 *
1'
#1710
0'
#1715
b10101011 *
1'
#1720
0'
#1725
b10101100 *
1'
#1730
0'
#1735
b10101101 *
1'
#1740
0'
#1745
b10101110 *
1'
#1750
0'
#1755
b10101111 *
1'
#1760
0'
#1765
b10110000 *
1'
#1770
0'
#1775
b10110001 *
1'
#1780
0'
#1785
b10110010 *
1'
#1790
0'
#1795
b10110011 *
1'
#1800
0'
#1805
1)
b10110100 *
1'
#1810
0'
#1815
0)
b10110101 *
1'
#1820
0'
#1825
b10110110 *
1'
#1830
0'
#1835
b10110111 *
1'
#1840
0'
#1845
b10111000 *
1'
#1850
0'
#1855
b10111001 *
1'
#1860
0'
#1865
b10111010 *
1'
#1870
0'
#1875
b10111011 *
1'
#1880
0'
#1885
b10111100 *
1'
#1890
0'
#1895
b10111101 *
1'
#1900
0'
#1905
b10111110 *
1'
#1910
0'
#1915
b10111111 *
1'
#1920
0'
#1925
b11000000 *
1'
#1930
0'
#1935
b11000001 *
1'
#1940
0'
#1945
b11000010 *
1'
#1950
0'
#1955
b11000011 *
1'
#1960
0'
#1965
b11000100 *
1'
#1970
0'
#1975
b11000101 *
1'
#1980
0'
#1985
b11000110 *
1'
#1990
0'
#1995
b11000111 *
1'
