fsm_assignments/problem3_vending/vending_mealy.v
module vending_mealy(
    input  wire clk,
    input  wire rst,          // sync active-high reset
    input  wire [1:0] coin,   // 01=5, 10=10, 00=idle

    output reg  dispense,     // 1-cycle pulse
    output reg  chg5          // 1-cycle pulse when 25
);

    localparam S0  = 2'b00;   // total = 0
    localparam S5  = 2'b01;   // total = 5
    localparam S10 = 2'b10;   // total = 10
    localparam S15 = 2'b11;   // total = 15

    reg [1:0] state, next_state;

    // State register
    always @(posedge clk) begin
        if (rst)
            state <= S0;
        else
            state <= next_state;
    end

    // Next-state logic + Mealy outputs
    always @(*) begin
        next_state = state;
        dispense = 0;
        chg5 = 0;

        case (state)
            S0: begin
                if (coin == 2'b01) next_state = S5;       // +5
                else if (coin == 2'b10) next_state = S10; // +10
            end

            S5: begin
                if (coin == 2'b01) next_state = S10;      // 5+5=10
                else if (coin == 2'b10) next_state = S15; // 5+10=15
            end

            S10: begin
                if (coin == 2'b01) next_state = S15;      // 10+5=15
                else if (coin == 2'b10) begin             // 10+10=20 → vend
                    dispense = 1;
                    next_state = S0;
                end
            end

            S15: begin
                if (coin == 2'b01) begin                  // 15+5=20 → vend+chg
                    dispense = 1;
                    chg5 = 1;
                    next_state = S0;
                end
                else if (coin == 2'b10) begin             // 15+10=25 → vend
                    dispense = 1;
                    next_state = S0;
                end
            end
        endcase
    end
endmodule

fsm_assignments/problem3_vending/tb_vending_mealy.v
module tb_vending_mealy;
    reg clk, rst;
    reg [1:0] coin;
    wire dispense, chg5;

    vending_mealy dut(.clk(clk), .rst(rst), .coin(coin),
                      .dispense(dispense), .chg5(chg5));

    always #5 clk = ~clk;  // clock

    initial begin
        $dumpfile("dump.vcd");
        $dumpvars(0, tb_vending_mealy);

        clk = 0; rst = 1; coin = 2'b00;
        #12 rst = 0;

        // Test cases
        put10(); put10();          // 10+10 = vend
        put5(); put5(); put10();   // 5+5+10 = vend
        put10(); put5(); put10();  // 10+5+10 = vend+chg

        repeat (5) @(posedge clk);
        $finish;
    end

    // Helper tasks
    task put5; begin
        @(posedge clk) coin = 2'b01;
        @(posedge clk) coin = 2'b00;
    end endtask

    task put10; begin
        @(posedge clk) coin = 2'b10;
        @(posedge clk) coin = 2'b00;
    end endtask
endmodule

fsm_assignments/problem3_vending/waves/dump.vcd
$date
	Tue Aug 19 10:35:45 2025
$end
$version
	Icarus Verilog
$end
$timescale
	1s
$end
$scope module tb_vending_mealy $end
$var wire 1 ! dispense $end
$var wire 1 " chg5 $end
$var reg 1 # clk $end
$var reg 2 $ coin [1:0] $end
$var reg 1 % rst $end
$scope module dut $end
$var wire 1 # clk $end
$var wire 2 & coin [1:0] $end
$var wire 1 % rst $end
$var parameter 2 ' S0 $end
$var parameter 2 ( S10 $end
$var parameter 2 ) S15 $end
$var parameter 2 * S5 $end
$var reg 1 " chg5 $end
$var reg 1 ! dispense $end
$var reg 2 + next_state [1:0] $end
$var reg 2 , state [1:0] $end
$upscope $end
$scope task put10 $end
$upscope $end
$scope task put5 $end
$upscope $end
$upscope $end
$enddefinitions $end
$comment Show the parameter values. $end
$dumpall
b1 *
b11 )
b10 (
b0 '
$end
#0
$dumpvars
bx ,
bx +
b0 &
1%
b0 $
0#
0"
0!
$end
#5
b0 +
b0 ,
1#
#10
0#
#12
0%
#15
b10 +
b10 $
b10 &
1#
#20
0#
#25
b10 ,
b10 +
b0 $
b0 &
1#
#30
0#
#35
b0 +
1!
b10 $
b10 &
1#
#40
0#
#45
b0 ,
0!
b0 +
b0 $
b0 &
1#
#50
0#
#55
b1 +
b1 $
b1 &
1#
#60
0#
#65
b1 ,
b1 +
b0 $
b0 &
1#
#70
0#
#75
b10 +
b1 $
b1 &
1#
#80
0#
#85
b10 ,
b10 +
b0 $
b0 &
1#
#90
0#
#95
b0 +
1!
b10 $
b10 &
1#
#100
0#
#105
b0 ,
0!
b0 +
b0 $
b0 &
1#
#110
0#
#115
b10 +
b10 $
b10 &
1#
#120
0#
#125
b10 ,
b10 +
b0 $
b0 &
1#
#130
0#
#135
b11 +
b1 $
b1 &
1#
#140
0#
#145
b11 ,
b11 +
b0 $
b0 &
1#
#150
0#
#155
b0 +
1!
b10 $
b10 &
1#
#160
0#
#165
b0 ,
0!
b0 +
b0 $
b0 &
1#
