fsm_assignments/problem4_master_slave/slave_fsm.v
module slave_fsm(
    input  wire       clk,
    input  wire       rst,
    input  wire       req,
    input  wire [7:0] data_in,
    output reg        ack,
    output reg  [7:0] last_byte
);
    localparam WAIT=2'd0, ACK=2'd1;

    reg [1:0] state, next_state;
    reg [1:0] cnt;

    always @(posedge clk) begin
        if (rst) begin
            state <= WAIT;
            cnt   <= 2'd0;
            ack   <= 1'b0;
            last_byte <= 8'd0;
        end else begin
            state <= next_state;
        end
    end

    always @(*) begin
        next_state = state;
        ack = (state == ACK);
        case (state)
            WAIT: if (req) next_state = ACK;
            ACK:  if (cnt == 2'd1) next_state = WAIT; // 2 cycles high
        endcase
    end

    always @(posedge clk) begin
        if (rst) begin
            cnt <= 2'd0;
        end else begin
            case (state)
                WAIT: begin
                    cnt <= 2'd0;
                    if (req) last_byte <= data_in; // latch on req
                end
                ACK:  cnt <= cnt + 2'd1;
            endcase
        end
    end
endmodule

fsm_assignments/problem4_master_slave/master_fsm.v
module master_fsm(
    input  wire       clk,
    input  wire       rst,
    input  wire       ack,
    output reg        req,
    output reg  [7:0] data,
    output reg        done
);
    localparam IDLE=3'd0, LOAD=3'd1, WAIT_ACK1=3'd2, WAIT_ACK0=3'd3, NEXT=3'd4, DONE=3'd5;

    reg [2:0] state, next_state;
    reg [1:0] idx;

    // simple 4-byte ROM
    wire [7:0] rom0 = 8'hA1;
    wire [7:0] rom1 = 8'hB2;
    wire [7:0] rom2 = 8'hC3;
    wire [7:0] rom3 = 8'hD4;

    always @(posedge clk) begin
        if (rst) begin
            state <= IDLE;
            idx   <= 2'd0;
            data  <= 8'd0;
            req   <= 1'b0;
            done  <= 1'b0;
        end else begin
            state <= next_state;
        end
    end

    always @(*) begin
        next_state = state;
        req  = 1'b0;
        done = 1'b0;

        case (state)
            IDLE:       next_state = LOAD;
            LOAD: begin
                req = 1'b1;
                next_state = WAIT_ACK1;
            end
            WAIT_ACK1: begin
                req = 1'b1;
                if (ack) next_state = WAIT_ACK0;
            end
            WAIT_ACK0: begin
                req = 1'b1;
                if (!ack) next_state = NEXT;
            end
            NEXT: begin
                if (idx == 2'd3) next_state = DONE;
                else              next_state = LOAD;
            end
            DONE: begin
                done = 1'b1;
                next_state = IDLE;
            end
        endcase
    end

    // data/idx updates
    always @(posedge clk) begin
        if (rst) begin
            idx  <= 2'd0;
            data <= 8'd0;
        end else begin
            case (state)
                IDLE: begin
                    idx  <= 2'd0;
                    data <= 8'd0;
                end
                LOAD: begin
                    case (idx)
                        2'd0: data <= rom0;
                        2'd1: data <= rom1;
                        2'd2: data <= rom2;
                        2'd3: data <= rom3;
                    endcase
                end
                NEXT: begin
                    if (idx != 2'd3) idx <= idx + 2'd1;
                end
            endcase
        end
    end
endmodule

fsm_assignments/problem4_master_slave/link_top.v
module link_top(
    input  wire       clk,
    input  wire       rst,
    output wire       done,
    output wire [7:0] last_byte
);
    wire req, ack;
    wire [7:0] data;

    master_fsm u_master(
        .clk(clk), .rst(rst), .ack(ack),
        .req(req), .data(data), .done(done)
    );

    slave_fsm u_slave(
        .clk(clk), .rst(rst), .req(req), .data_in(data),
        .ack(ack), .last_byte(last_byte)
    );
endmodule

fsm_assignments/problem4_master_slave/tb_link.v
module tb_link;
    reg clk, rst;
    wire done;
    wire [7:0] last_byte;

    link_top dut(.clk(clk), .rst(rst), .done(done), .last_byte(last_byte));

    always #5 clk = ~clk;

    initial begin
        $dumpfile("dump.vcd");
        $dumpvars(0, tb_link);

        clk = 0; rst = 1;
        #20 rst = 0;

        // run long enough to see multiple bursts
        repeat (200) @(posedge clk);
        $finish;
    end
endmodule

fsm_assignments/problem4_master_slave/waves/dump.vcd
$date
	Tue Aug 19 10:41:22 2025
$end
$version
	Icarus Verilog
$end
$timescale
	1s
$end
$scope module tb_link $end
$var wire 8 ! last_byte [7:0] $end
$var wire 1 " done $end
$var reg 1 # clk $end
$var reg 1 $ rst $end
$scope module dut $end
$var wire 1 # clk $end
$var wire 1 $ rst $end
$var wire 1 % req $end
$var wire 8 & last_byte [7:0] $end
$var wire 1 " done $end
$var wire 8 ' data [7:0] $end
$var wire 1 ( ack $end
$scope module u_master $end
$var wire 1 # clk $end
$var wire 8 ) rom0 [7:0] $end
$var wire 8 * rom1 [7:0] $end
$var wire 8 + rom2 [7:0] $end
$var wire 8 , rom3 [7:0] $end
$var wire 1 $ rst $end
$var wire 1 ( ack $end
$var parameter 3 - DONE $end
$var parameter 3 . IDLE $end
$var parameter 3 / LOAD $end
$var parameter 3 0 NEXT $end
$var parameter 3 1 WAIT_ACK0 $end
$var parameter 3 2 WAIT_ACK1 $end
$var reg 8 3 data [7:0] $end
$var reg 1 " done $end
$var reg 2 4 idx [1:0] $end
$var reg 3 5 next_state [2:0] $end
$var reg 1 % req $end
$var reg 3 6 state [2:0] $end
$upscope $end
$scope module u_slave $end
$var wire 1 # clk $end
$var wire 8 7 data_in [7:0] $end
$var wire 1 % req $end
$var wire 1 $ rst $end
$var parameter 2 8 ACK $end
$var parameter 2 9 WAIT $end
$var reg 1 ( ack $end
$var reg 2 : cnt [1:0] $end
$var reg 8 ; last_byte [7:0] $end
$var reg 2 < next_state [1:0] $end
$var reg 2 = state [1:0] $end
$upscope $end
$upscope $end
$upscope $end
$enddefinitions $end
$comment Show the parameter values. $end
$dumpall
b0 9
b1 8
b10 2
b11 1
b100 0
b1 /
b0 .
b101 -
$end
#0
$dumpvars
bx =
bx <
bx ;
bx :
bx 7
bx 6
bx 5
bx 4
bx 3
b11010100 ,
b11000011 +
b10110010 *
b10100001 )
x(
bx '
bx &
x%
1$
0#
x"
bx !
$end
#5
b1 5
b0 <
0"
0%
b0 6
b0 '
b0 3
b0 7
b0 4
b0 !
b0 &
b0 ;
0(
b0 =
b0 :
1#
#10
0#
#15
1#
#20
0#
0$
#25
b1 <
b10 5
1%
b1 6
1#
#30
0#
#35
b11 5
1(
1%
b1 =
b10100001 '
b10100001 3
b10100001 7
b10 6
1#
#40
0#
#45
1%
b0 <
b11 6
b1 :
1#
#50
0#
#55
b100 5
1%
b1 <
0(
b10 :
b0 =
1#
#60
0#
#65
b1 5
0%
1(
b100 6
b1 =
b10100001 !
b10100001 &
b10100001 ;
b0 :
1#
#70
0#
#75
b0 <
b10 5
1%
b1 :
b1 4
b1 6
1#
#80
0#
#85
1%
b1 <
0(
b10 6
b10110010 '
b10110010 3
b10110010 7
b0 =
b10 :
1#
#90
0#
#95
b11 5
1%
1(
b10110010 !
b10110010 &
b10110010 ;
b0 :
b1 =
1#
#100
0#
#105
1%
b0 <
b11 6
b1 :
1#
#110
0#
#115
b100 5
1%
b1 <
0(
b10 :
b0 =
1#
#120
0#
#125
b1 5
0%
1(
b100 6
b1 =
b0 :
1#
#130
0#
#135
b0 <
b10 5
1%
b1 :
b10 4
b1 6
1#
#140
0#
#145
1%
b1 <
0(
b10 6
b11000011 '
b11000011 3
b11000011 7
b0 =
b10 :
1#
#150
0#
#155
b11 5
1%
1(
b11000011 !
b11000011 &
b11000011 ;
b0 :
b1 =
1#
#160
0#
#165
1%
b0 <
b11 6
b1 :
1#
#170
0#
#175
b100 5
1%
b1 <
0(
b10 :
b0 =
1#
#180
0#
#185
b1 5
0%
1(
b100 6
b1 =
b0 :
1#
#190
0#
#195
b0 <
b10 5
1%
b1 :
b11 4
b1 6
1#
#200
0#
#205
1%
b1 <
0(
b10 6
b11010100 '
b11010100 3
b11010100 7
b0 =
b10 :
1#
#210
0#
#215
b11 5
1%
1(
b11010100 !
b11010100 &
b11010100 ;
b0 :
b1 =
1#
#220
0#
#225
1%
b0 <
b11 6
b1 :
1#
#230
0#
#235
b100 5
1%
b1 <
0(
b10 :
b0 =
1#
#240
0#
#245
b101 5
0%
1(
b100 6
b1 =
b0 :
1#
#250
0#
#255
b0 <
b0 5
1"
b1 :
b101 6
1#
#260
0#
#265
b1 5
0"
0(
b0 6
b0 =
b10 :
1#
#270
0#
#275
b1 <
b10 5
1%
b0 :
b0 '
b0 3
b0 7
b0 4
b1 6
1#
#280
0#
#285
b11 5
1%
1(
b10 6
b10100001 '
b10100001 3
b10100001 7
b1 =
b0 !
b0 &
b0 ;
1#
#290
0#
#295
b0 <
1%
b1 :
b11 6
1#
#300
0#
#305
b100 5
1%
b1 <
0(
b0 =
b10 :
1#
#310
0#
#315
1(
b1 5
0%
b10100001 !
b10100001 &
b10100001 ;
b0 :
b1 =
b100 6
1#
#320
0#
#325
b10 5
1%
b0 <
b1 6
b1 4
b1 :
1#
#330
0#
#335
b1 <
0(
b10 5
1%
b10 :
b0 =
b10110010 '
b10110010 3
b10110010 7
b10 6
1#
#340
0#
#345
b11 5
1%
1(
b1 =
b10110010 !
b10110010 &
b10110010 ;
b0 :
1#
#350
0#
#355
b0 <
1%
b1 :
b11 6
1#
#360
0#
#365
b100 5
1%
b1 <
0(
b0 =
b10 :
1#
#370
0#
#375
1(
b1 5
0%
b0 :
b1 =
b100 6
1#
#380
0#
#385
b10 5
1%
b0 <
b1 6
b10 4
b1 :
1#
#390
0#
#395
b1 <
0(
b10 5
1%
b10 :
b0 =
b11000011 '
b11000011 3
b11000011 7
b10 6
1#
#400
0#
#405
b11 5
1%
1(
b1 =
b11000011 !
b11000011 &
b11000011 ;
b0 :
1#
#410
0#
#415
b0 <
1%
b1 :
b11 6
1#
#420
0#
#425
b100 5
1%
b1 <
0(
b0 =
b10 :
1#
#430
0#
#435
1(
b1 5
0%
b0 :
b1 =
b100 6
1#
#440
0#
#445
b10 5
1%
b0 <
b1 6
b11 4
b1 :
1#
#450
0#
#455
b1 <
0(
b10 5
1%
b10 :
b0 =
b11010100 '
b11010100 3
b11010100 7
b10 6
1#
#460
0#
#465
b11 5
1%
1(
b1 =
b11010100 !
b11010100 &
b11010100 ;
b0 :
1#
#470
0#
#475
b0 <
1%
b1 :
b11 6
1#
#480
0#
#485
b100 5
1%
b1 <
0(
b0 =
b10 :
1#
#490
0#
#495
1(
b101 5
0%
b0 :
b1 =
b100 6
1#
#500
0#
#505
b0 5
1"
b0 <
b101 6
b1 :
1#
#510
0#
#515
0(
b1 5
0"
b10 :
b0 =
b0 6
1#
#520
0#
#525
b1 <
b10 5
1%
b1 6
b0 '
b0 3
b0 7
b0 4
b0 :
1#
#530
0#
#535
b11 5
1(
1%
b0 !
b0 &
b0 ;
b1 =
b10100001 '
b10100001 3
b10100001 7
b10 6
1#
#540
0#
#545
1%
b0 <
b11 6
b1 :
1#
#550
0#
#555
b100 5
1%
b1 <
0(
b10 :
b0 =
1#
#560
0#
#565
b1 5
0%
1(
b100 6
b1 =
b10100001 !
b10100001 &
b10100001 ;
b0 :
1#
#570
0#
#575
b0 <
b10 5
1%
b1 :
b1 4
b1 6
1#
#580
0#
#585
1%
b1 <
0(
b10 6
b10110010 '
b10110010 3
b10110010 7
b0 =
b10 :
1#
#590
0#
#595
b11 5
1%
1(
b10110010 !
b10110010 &
b10110010 ;
b0 :
b1 =
1#
#600
0#
#605
1%
b0 <
b11 6
b1 :
1#
#610
0#
#615
b100 5
1%
b1 <
0(
b10 :
b0 =
1#
#620
0#
#625
b1 5
0%
1(
b100 6
b1 =
b0 :
1#
#630
0#
#635
b0 <
b10 5
1%
b1 :
b10 4
b1 6
1#
#640
0#
#645
1%
b1 <
0(
b10 6
b11000011 '
b11000011 3
b11000011 7
b0 =
b10 :
1#
#650
0#
#655
b11 5
1%
1(
b11000011 !
b11000011 &
b11000011 ;
b0 :
b1 =
1#
#660
0#
#665
1%
b0 <
b11 6
b1 :
1#
#670
0#
#675
b100 5
1%
b1 <
0(
b10 :
b0 =
1#
#680
0#
#685
b1 5
0%
1(
b100 6
b1 =
b0 :
1#
#690
0#
#695
b0 <
b10 5
1%
b1 :
b11 4
b1 6
1#
#700
0#
#705
1%
b1 <
0(
b10 6
b11010100 '
b11010100 3
b11010100 7
b0 =
b10 :
1#
#710
0#
#715
b11 5
1%
1(
b11010100 !
b11010100 &
b11010100 ;
b0 :
b1 =
1#
#720
0#
#725
1%
b0 <
b11 6
b1 :
1#
#730
0#
#735
b100 5
1%
b1 <
0(
b10 :
b0 =
1#
#740
0#
#745
b101 5
0%
1(
b100 6
b1 =
b0 :
1#
#750
0#
#755
b0 <
b0 5
1"
b1 :
b101 6
1#
#760
0#
#765
b1 5
0"
0(
b0 6
b0 =
b10 :
1#
#770
0#
#775
b1 <
b10 5
1%
b0 :
b0 '
b0 3
b0 7
b0 4
b1 6
1#
#780
0#
#785
b11 5
1%
1(
b10 6
b10100001 '
b10100001 3
b10100001 7
b1 =
b0 !
b0 &
b0 ;
1#
#790
0#
#795
b0 <
1%
b1 :
b11 6
1#
#800
0#
#805
b100 5
1%
b1 <
0(
b0 =
b10 :
1#
#810
0#
#815
1(
b1 5
0%
b10100001 !
b10100001 &
b10100001 ;
b0 :
b1 =
b100 6
1#
#820
0#
#825
b10 5
1%
b0 <
b1 6
b1 4
b1 :
1#
#830
0#
#835
b1 <
0(
b10 5
1%
b10 :
b0 =
b10110010 '
b10110010 3
b10110010 7
b10 6
1#
#840
0#
#845
b11 5
1%
1(
b1 =
b10110010 !
b10110010 &
b10110010 ;
b0 :
1#
#850
0#
#855
b0 <
1%
b1 :
b11 6
1#
#860
0#
#865
b100 5
1%
b1 <
0(
b0 =
b10 :
1#
#870
0#
#875
1(
b1 5
0%
b0 :
b1 =
b100 6
1#
#880
0#
#885
b10 5
1%
b0 <
b1 6
b10 4
b1 :
1#
#890
0#
#895
b1 <
0(
b10 5
1%
b10 :
b0 =
b11000011 '
b11000011 3
b11000011 7
b10 6
1#
#900
0#
#905
b11 5
1%
1(
b1 =
b11000011 !
b11000011 &
b11000011 ;
b0 :
1#
#910
0#
#915
b0 <
1%
b1 :
b11 6
1#
#920
0#
#925
b100 5
1%
b1 <
0(
b0 =
b10 :
1#
#930
0#
#935
1(
b1 5
0%
b0 :
b1 =
b100 6
1#
#940
0#
#945
b10 5
1%
b0 <
b1 6
b11 4
b1 :
1#
#950
0#
#955
b1 <
0(
b10 5
1%
b10 :
b0 =
b11010100 '
b11010100 3
b11010100 7
b10 6
1#
#960
0#
#965
b11 5
1%
1(
b1 =
b11010100 !
b11010100 &
b11010100 ;
b0 :
1#
#970
0#
#975
b0 <
1%
b1 :
b11 6
1#
#980
0#
#985
b100 5
1%
b1 <
0(
b0 =
b10 :
1#
#990
0#
#995
1(
b101 5
0%
b0 :
b1 =
b100 6
1#
#1000
0#
#1005
b0 5
1"
b0 <
b101 6
b1 :
1#
#1010
0#
#1015
0(
b1 5
0"
b10 :
b0 =
b0 6
1#
#1020
0#
#1025
b1 <
b10 5
1%
b1 6
b0 '
b0 3
b0 7
b0 4
b0 :
1#
#1030
0#
#1035
b11 5
1(
1%
b0 !
b0 &
b0 ;
b1 =
b10100001 '
b10100001 3
b10100001 7
b10 6
1#
#1040
0#
#1045
1%
b0 <
b11 6
b1 :
1#
#1050
0#
#1055
b100 5
1%
b1 <
0(
b10 :
b0 =
1#
#1060
0#
#1065
b1 5
0%
1(
b100 6
b1 =
b10100001 !
b10100001 &
b10100001 ;
b0 :
1#
#1070
0#
#1075
b0 <
b10 5
1%
b1 :
b1 4
b1 6
1#
#1080
0#
#1085
1%
b1 <
0(
b10 6
b10110010 '
b10110010 3
b10110010 7
b0 =
b10 :
1#
#1090
0#
#1095
b11 5
1%
1(
b10110010 !
b10110010 &
b10110010 ;
b0 :
b1 =
1#
#1100
0#
#1105
1%
b0 <
b11 6
b1 :
1#
#1110
0#
#1115
b100 5
1%
b1 <
0(
b10 :
b0 =
1#
#1120
0#
#1125
b1 5
0%
1(
b100 6
b1 =
b0 :
1#
#1130
0#
#1135
b0 <
b10 5
1%
b1 :
b10 4
b1 6
1#
#1140
0#
#1145
1%
b1 <
0(
b10 6
b11000011 '
b11000011 3
b11000011 7
b0 =
b10 :
1#
#1150
0#
#1155
b11 5
1%
1(
b11000011 !
b11000011 &
b11000011 ;
b0 :
b1 =
1#
#1160
0#
#1165
1%
b0 <
b11 6
b1 :
1#
#1170
0#
#1175
b100 5
1%
b1 <
0(
b10 :
b0 =
1#
#1180
0#
#1185
b1 5
0%
1(
b100 6
b1 =
b0 :
1#
#1190
0#
#1195
b0 <
b10 5
1%
b1 :
b11 4
b1 6
1#
#1200
0#
#1205
1%
b1 <
0(
b10 6
b11010100 '
b11010100 3
b11010100 7
b0 =
b10 :
1#
#1210
0#
#1215
b11 5
1%
1(
b11010100 !
b11010100 &
b11010100 ;
b0 :
b1 =
1#
#1220
0#
#1225
1%
b0 <
b11 6
b1 :
1#
#1230
0#
#1235
b100 5
1%
b1 <
0(
b10 :
b0 =
1#
#1240
0#
#1245
b101 5
0%
1(
b100 6
b1 =
b0 :
1#
#1250
0#
#1255
b0 <
b0 5
1"
b1 :
b101 6
1#
#1260
0#
#1265
b1 5
0"
0(
b0 6
b0 =
b10 :
1#
#1270
0#
#1275
b1 <
b10 5
1%
b0 :
b0 '
b0 3
b0 7
b0 4
b1 6
1#
#1280
0#
#1285
b11 5
1%
1(
b10 6
b10100001 '
b10100001 3
b10100001 7
b1 =
b0 !
b0 &
b0 ;
1#
#1290
0#
#1295
b0 <
1%
b1 :
b11 6
1#
#1300
0#
#1305
b100 5
1%
b1 <
0(
b0 =
b10 :
1#
#1310
0#
#1315
1(
b1 5
0%
b10100001 !
b10100001 &
b10100001 ;
b0 :
b1 =
b100 6
1#
#1320
0#
#1325
b10 5
1%
b0 <
b1 6
b1 4
b1 :
1#
#1330
0#
#1335
b1 <
0(
b10 5
1%
b10 :
b0 =
b10110010 '
b10110010 3
b10110010 7
b10 6
1#
#1340
0#
#1345
b11 5
1%
1(
b1 =
b10110010 !
b10110010 &
b10110010 ;
b0 :
1#
#1350
0#
#1355
b0 <
1%
b1 :
b11 6
1#
#1360
0#
#1365
b100 5
1%
b1 <
0(
b0 =
b10 :
1#
#1370
0#
#1375
1(
b1 5
0%
b0 :
b1 =
b100 6
1#
#1380
0#
#1385
b10 5
1%
b0 <
b1 6
b10 4
b1 :
1#
#1390
0#
#1395
b1 <
0(
b10 5
1%
b10 :
b0 =
b11000011 '
b11000011 3
b11000011 7
b10 6
1#
#1400
0#
#1405
b11 5
1%
1(
b1 =
b11000011 !
b11000011 &
b11000011 ;
b0 :
1#
#1410
0#
#1415
b0 <
1%
b1 :
b11 6
1#
#1420
0#
#1425
b100 5
1%
b1 <
0(
b0 =
b10 :
1#
#1430
0#
#1435
1(
b1 5
0%
b0 :
b1 =
b100 6
1#
#1440
0#
#1445
b10 5
1%
b0 <
b1 6
b11 4
b1 :
1#
#1450
0#
#1455
b1 <
0(
b10 5
1%
b10 :
b0 =
b11010100 '
b11010100 3
b11010100 7
b10 6
1#
#1460
0#
#1465
b11 5
1%
1(
b1 =
b11010100 !
b11010100 &
b11010100 ;
b0 :
1#
#1470
0#
#1475
b0 <
1%
b1 :
b11 6
1#
#1480
0#
#1485
b100 5
1%
b1 <
0(
b0 =
b10 :
1#
#1490
0#
#1495
1(
b101 5
0%
b0 :
b1 =
b100 6
1#
#1500
0#
#1505
b0 5
1"
b0 <
b101 6
b1 :
1#
#1510
0#
#1515
0(
b1 5
0"
b10 :
b0 =
b0 6
1#
#1520
0#
#1525
b1 <
b10 5
1%
b1 6
b0 '
b0 3
b0 7
b0 4
b0 :
1#
#1530
0#
#1535
b11 5
1(
1%
b0 !
b0 &
b0 ;
b1 =
b10100001 '
b10100001 3
b10100001 7
b10 6
1#
#1540
0#
#1545
1%
b0 <
b11 6
b1 :
1#
#1550
0#
#1555
b100 5
1%
b1 <
0(
b10 :
b0 =
1#
#1560
0#
#1565
b1 5
0%
1(
b100 6
b1 =
b10100001 !
b10100001 &
b10100001 ;
b0 :
1#
#1570
0#
#1575
b0 <
b10 5
1%
b1 :
b1 4
b1 6
1#
#1580
0#
#1585
1%
b1 <
0(
b10 6
b10110010 '
b10110010 3
b10110010 7
b0 =
b10 :
1#
#1590
0#
#1595
b11 5
1%
1(
b10110010 !
b10110010 &
b10110010 ;
b0 :
b1 =
1#
#1600
0#
#1605
1%
b0 <
b11 6
b1 :
1#
#1610
0#
#1615
b100 5
1%
b1 <
0(
b10 :
b0 =
1#
#1620
0#
#1625
b1 5
0%
1(
b100 6
b1 =
b0 :
1#
#1630
0#
#1635
b0 <
b10 5
1%
b1 :
b10 4
b1 6
1#
#1640
0#
#1645
1%
b1 <
0(
b10 6
b11000011 '
b11000011 3
b11000011 7
b0 =
b10 :
1#
#1650
0#
#1655
b11 5
1%
1(
b11000011 !
b11000011 &
b11000011 ;
b0 :
b1 =
1#
#1660
0#
#1665
1%
b0 <
b11 6
b1 :
1#
#1670
0#
#1675
b100 5
1%
b1 <
0(
b10 :
b0 =
1#
#1680
0#
#1685
b1 5
0%
1(
b100 6
b1 =
b0 :
1#
#1690
0#
#1695
b0 <
b10 5
1%
b1 :
b11 4
b1 6
1#
#1700
0#
#1705
1%
b1 <
0(
b10 6
b11010100 '
b11010100 3
b11010100 7
b0 =
b10 :
1#
#1710
0#
#1715
b11 5
1%
1(
b11010100 !
b11010100 &
b11010100 ;
b0 :
b1 =
1#
#1720
0#
#1725
1%
b0 <
b11 6
b1 :
1#
#1730
0#
#1735
b100 5
1%
b1 <
0(
b10 :
b0 =
1#
#1740
0#
#1745
b101 5
0%
1(
b100 6
b1 =
b0 :
1#
#1750
0#
#1755
b0 <
b0 5
1"
b1 :
b101 6
1#
#1760
0#
#1765
b1 5
0"
0(
b0 6
b0 =
b10 :
1#
#1770
0#
#1775
b1 <
b10 5
1%
b0 :
b0 '
b0 3
b0 7
b0 4
b1 6
1#
#1780
0#
#1785
b11 5
1%
1(
b10 6
b10100001 '
b10100001 3
b10100001 7
b1 =
b0 !
b0 &
b0 ;
1#
#1790
0#
#1795
b0 <
1%
b1 :
b11 6
1#
#1800
0#
#1805
b100 5
1%
b1 <
0(
b0 =
b10 :
1#
#1810
0#
#1815
1(
b1 5
0%
b10100001 !
b10100001 &
b10100001 ;
b0 :
b1 =
b100 6
1#
#1820
0#
#1825
b10 5
1%
b0 <
b1 6
b1 4
b1 :
1#
#1830
0#
#1835
b1 <
0(
b10 5
1%
b10 :
b0 =
b10110010 '
b10110010 3
b10110010 7
b10 6
1#
#1840
0#
#1845
b11 5
1%
1(
b1 =
b10110010 !
b10110010 &
b10110010 ;
b0 :
1#
#1850
0#
#1855
b0 <
1%
b1 :
b11 6
1#
#1860
0#
#1865
b100 5
1%
b1 <
0(
b0 =
b10 :
1#
#1870
0#
#1875
1(
b1 5
0%
b0 :
b1 =
b100 6
1#
#1880
0#
#1885
b10 5
1%
b0 <
b1 6
b10 4
b1 :
1#
#1890
0#
#1895
b1 <
0(
b10 5
1%
b10 :
b0 =
b11000011 '
b11000011 3
b11000011 7
b10 6
1#
#1900
0#
#1905
b11 5
1%
1(
b1 =
b11000011 !
b11000011 &
b11000011 ;
b0 :
1#
#1910
0#
#1915
b0 <
1%
b1 :
b11 6
1#
#1920
0#
#1925
b100 5
1%
b1 <
0(
b0 =
b10 :
1#
#1930
0#
#1935
1(
b1 5
0%
b0 :
b1 =
b100 6
1#
#1940
0#
#1945
b10 5
1%
b0 <
b1 6
b11 4
b1 :
1#
#1950
0#
#1955
b1 <
0(
b10 5
1%
b10 :
b0 =
b11010100 '
b11010100 3
b11010100 7
b10 6
1#
#1960
0#
#1965
b11 5
1%
1(
b1 =
b11010100 !
b11010100 &
b11010100 ;
b0 :
1#
#1970
0#
#1975
b0 <
1%
b1 :
b11 6
1#
#1980
0#
#1985
b100 5
1%
b1 <
0(
b0 =
b10 :
1#
#1990
0#
#1995
1(
b101 5
0%
b0 :
b1 =
b100 6
1#
#2000
0#
#2005
b0 5
1"
b0 <
b101 6
b1 :
1#
#2010
0#
#2015
0(
b1 5
0"
b10 :
b0 =
b0 6
1#
